bulstem/__init__.py
bulstem/stem.py
bulstem/stemrules/stem_rules_context_1_utf8.txt
bulstem/stemrules/stem_rules_context_2_utf8.txt
bulstem/stemrules/stem_rules_context_3_utf8.txt
bulstem-0.3.3.dist-info/LICENSE
bulstem-0.3.3.dist-info/METADATA
bulstem-0.3.3.dist-info/WHEEL
bulstem-0.3.3.dist-info/top_level.txt
bulstem-0.3.3.dist-info/RECORD
