Metadata-Version: 2.1
Name: bulstem
Version: 0.3.3
Summary: Python version of the BulStem stemming algorithm
Home-page: https://github.com/mhardalov/bulstem-py
Author: Momchil Hardalov
Author-email: momchil.hardalov@gmail.com
License: Apache License, Version 2.0
Keywords: NLP stemmer Bulgarian bulstem
Platform: UNKNOWN
Classifier: Intended Audience :: Developers
Classifier: Intended Audience :: Education
Classifier: Intended Audience :: Science/Research
Classifier: License :: OSI Approved :: Apache Software License
Classifier: Programming Language :: Python :: 3
Classifier: Programming Language :: Python :: 3.6
Classifier: Programming Language :: Python :: 3.7
Classifier: Programming Language :: Python :: 3.8
Classifier: Topic :: Scientific/Engineering :: Artificial Intelligence
Classifier: Topic :: Text Processing
Classifier: Topic :: Text Processing :: Linguistic
Requires-Python: >=3.6.0
Provides-Extra: testing
Requires-Dist: pytest ; extra == 'testing'
Requires-Dist: nltk ; extra == 'testing'
